<?xml version="1.0" encoding="UTF-8"?>
<objects serializationModel="Studio.02.01.00">
	<object class="AudioFile" id="{505bb086-2b7e-40c4-8f90-1048a05179d3}">
		<property name="assetPath">
			<value>Friends Zone/7. Reklame.mp3</value>
		</property>
		<property name="isStreaming">
			<value>true</value>
		</property>
		<property name="frequencyInKHz">
			<value>44.0999985</value>
		</property>
		<property name="channelCount">
			<value>2</value>
		</property>
		<property name="length">
			<value>21.002448979591836</value>
		</property>
		<relationship name="masterAssetFolder">
			<destination>{bb2822c3-20b2-43c3-8cef-6858d5cfa859}</destination>
		</relationship>
	</object>
</objects>
